paraxor_schema/__init__.py
paraxor_schema/schema.py
paraxor_schema/tests/__init__.py
paraxor_schema/tests/test_schema.py
mailman_schema-1.0.0.dist-info/LICENSE
mailman_schema-1.0.0.dist-info/METADATA
mailman_schema-1.0.0.dist-info/WHEEL
mailman_schema-1.0.0.dist-info/entry_points.txt
mailman_schema-1.0.0.dist-info/top_level.txt
mailman_schema-1.0.0.dist-info/RECORD
